{"tasks":[{"id":"4630d24b-48d1-4b15-b338-e235c4017cba","updatedFields":{"id":"4630d24b-48d1-4b15-b338-e235c4017cba","title":"Desafio Nodejs","description":"Realizar um desafio para concluir o primeiro modulo do curso de nodejs na plataforma rocketseat","completed_at":"Sun Mar 10 2024 14:26:11 GMT-0300 (Brasilia Standard Time)","create_at":"Sun Mar 10 2024 14:25:54 GMT-0300 (Brasilia Standard Time)","updated_at":"Sun Mar 10 2024 14:25:54 GMT-0300 (Brasilia Standard Time)"}},{"id":"18a38e30-2dce-41ac-9575-96090835c89b","title":"Desafio Nodejs","description":"Realizar um desafio para concluir o primeiro modulo do curso de nodejs na plataforma rocketseat","completed_at":null,"create_at":"Sun Mar 10 2024 14:25:55 GMT-0300 (Brasilia Standard Time)","updated_at":"Sun Mar 10 2024 14:25:55 GMT-0300 (Brasilia Standard Time)"}]}